{"cameraMode":{"drawMode":0,"name":"Shaded","section":"Shading Mode"},"sceneLighting":true,"audioPlay":false,"sceneViewState":{"m_AlwaysRefresh":false,"showFog":true,"showSkybox":true,"showFlares":true,"showImageEffects":true,"showParticleSystems":true,"showVisualEffectGraphs":true,"m_FxEnabled":true},"in2DMode":false,"pivot":{"x":5.025481700897217,"y":-5.780655860900879,"z":1.6865533590316773},"rotation":{"x":-0.3965834379196167,"y":-0.04486418142914772,"z":0.01940888725221157,"w":-0.9166962504386902},"size":10.0,"orthographic":false}